utils/__init__.py
utils/bmo_mail.py
utils/handle_date.py
utils/ini_parser.py
ops_tool_kit-0.1.dist-info/LICENSE
ops_tool_kit-0.1.dist-info/METADATA
ops_tool_kit-0.1.dist-info/WHEEL
ops_tool_kit-0.1.dist-info/top_level.txt
ops_tool_kit-0.1.dist-info/RECORD
