Metadata-Version: 2.2
Name: ops_tool_kit
Version: 0.1
Summary: Personal tool kit
Home-page: https://github.com/zlz2013
Author: Coder_lz
Author-email: 229165631@qq.com
Classifier: Programming Language :: Python :: 3
License-File: LICENSE
Dynamic: author
Dynamic: author-email
Dynamic: classifier
Dynamic: description-content-type
Dynamic: home-page
Dynamic: summary
